setup.py
k_distributions/Binomialdistribution.py
k_distributions/Gaussiandistribution.py
k_distributions/Generaldistribution.py
k_distributions/__init__.py
k_distributions.egg-info/PKG-INFO
k_distributions.egg-info/SOURCES.txt
k_distributions.egg-info/dependency_links.txt
k_distributions.egg-info/not-zip-safe
k_distributions.egg-info/top_level.txt