Metadata-Version: 1.0
Name: k-distributions
Version: 0.1
Summary: Gaussian and Binomial distributions
Home-page: UNKNOWN
Author: Kyaw Thu Htun
Author-email: korv.dk97@gmail.com
License: UNKNOWN
Platform: UNKNOWN
